Phi/__init__.py
Phi/finished_methods.py
IRonTest3-0.0.1.dist-info/LICENSE
IRonTest3-0.0.1.dist-info/METADATA
IRonTest3-0.0.1.dist-info/WHEEL
IRonTest3-0.0.1.dist-info/top_level.txt
IRonTest3-0.0.1.dist-info/RECORD
